dtx_assessment_api/__init__.py
dtx_assessment_api/finding.py
dtx_assessment_api/finding_client.py
dtx_assessment_api/utils.py
dtx_assessment_api-0.10.1.dist-info/METADATA
dtx_assessment_api-0.10.1.dist-info/WHEEL
dtx_assessment_api-0.10.1.dist-info/RECORD
