Metadata-Version: 2.1
Name: dtx-assessment-api
Version: 0.10.1
Summary: detoxio.ai - Assessment Findings to Platform syncup api client
Home-page: https://detoxio.ai
License: Apache-2.0
Author: detoxio.ai
Author-email: hello@detoxio.ai
Requires-Python: >=3.10,<4.0
Classifier: License :: OSI Approved :: Apache Software License
Classifier: Programming Language :: Python :: 3
Classifier: Programming Language :: Python :: 3.10
Classifier: Programming Language :: Python :: 3.11
Classifier: Programming Language :: Python :: 3.12
Classifier: Programming Language :: Python :: 3.13
Classifier: Topic :: Scientific/Engineering :: Artificial Intelligence
Classifier: Topic :: Security
Requires-Dist: detoxio-api-protocolbuffers-python
Requires-Dist: detoxio_api_grpc_python
Requires-Dist: pydantic (>=2.8.2,<3.0.0)
Requires-Dist: requests (>=2.32.3,<3.0.0)
Project-URL: Documentation, https://docs.detoxio.ai
